{
    "request": {
        "name": "Muammar al-Gaddafi",
        "title": "Dictator of Libya",
        "year": 1942,
        "month": 6,
        "day": 7,
        "hour": 8,
        "minute": 35,
        "second": 0,
        "latitude": 31.05926,
        "longitude": 16.65905,
        "location": "Qasr Abu Hadi",
        "gender": "male",
        "agyat_rating": "AA",
        "advanced": "dead by gunshot, violent death, dictator",
        "about": "<p>Muammar Muhammad Abu Minyar al-Gaddafi[b] (c. 1942 – 20 October 2011) was a Libyan military officer, revolutionary, politician, and political theorist who ruled Libya from 1969 until his overthrow by Libyan rebel forces in 2011 during the First Libyan Civil War. He came to power through a bloodless military coup, first becoming Revolutionary Chairman of the Libyan Arab Republic from 1969 to 1977, Secretary General of the General People's Congress from 1977 to 1979, and then the Brotherly Leader of the Great Socialist People's Libyan Arab Jamahiriya from 1979 to 2011. Initially ideologically committed to Arab nationalism and Arab socialism, Gaddafi later ruled according to his own Third International Theory.</p><p>Born near Sirte, Italian Libya, to a poor Bedouin Arab family, Gaddafi became an Arab nationalist while at school in Sabha, later enrolling in the Royal Military Academy, Benghazi. He founded a revolutionary group known as the Free Officers movement which deposed the Western-backed Senussi monarchy of Idris in a 1969 coup. Gaddafi converted Libya into a republic governed by his Revolutionary Command Council. Ruling by decree, he deported Libya's Italian population and ejected its Western military bases. He strengthened ties to Arab nationalist governments and unsuccessfully advocated pan-Arab political union. An Islamic modernist, he introduced sharia law as the basis for the legal system and promoted Islamic socialism. He nationalized the oil industry and used the increasing state revenues to bolster the military, fund foreign revolutionaries, and implement social programs emphasizing housebuilding, healthcare and education projects. In 1973, he initiated a \"Popular Revolution\" with the formation of Basic People's Congresses, presented as a system of direct democracy, but retained personal control over major decisions. He outlined his Third International Theory that year in The Green Book.</p><p>In 1977, Gaddafi transformed Libya into a new socialist state called a Jamahiriya (\"state of the masses\"). He officially adopted a symbolic role in governance but remained head of both the military and the Revolutionary Committees responsible for policing and suppressing dissent. During the 1970s and 1980s, Libya's unsuccessful border conflicts with Egypt and Chad, support for foreign militants, and alleged responsibility for bombings of Pan Am Flight 103 and UTA Flight 772 left it increasingly isolated on the world stage. A particularly hostile relationship developed with Israel, the United States and the United Kingdom, resulting in the 1986 U.S. bombing of Libya and United Nations–imposed economic sanctions. From 1999, Gaddafi shunned pan-Arabism, and encouraged pan-Africanism and rapprochement with Western nations; he was Chairperson of the African Union from 2009 to 2010. Amid the 2011 Arab Spring, protests against widespread corruption and unemployment broke out in eastern Libya. The situation descended into civil war, in which NATO intervened militarily on the side of the anti-Gaddafist National Transitional Council (NTC). Gaddafi's government was overthrown; he retreated to Sirte only to be captured, tortured and killed by NTC militants.</p><p>A highly divisive figure, Gaddafi dominated Libya's politics for four decades and was the subject of a pervasive cult of personality. He was decorated with various awards and praised for his anti-imperialist stance, support for Arab—and then African—unity, as well as for significant development to the country after the discovery of oil reserves. Conversely, many Libyans strongly opposed Gaddafi's social and economic reforms; he was accused of various human rights violations. He was condemned by many as a dictator whose authoritarian administration systematically violated human rights and financed terrorism in the region and abroad.</p><p>"
    },
    "response": {
        "ascendant": {
            "asc_deg": 102.04196202499644,
            "ascendant": 4
        },
        "planets": {
            "Jupiter": {
                "degree": 66.24227708774902,
                "cusp_degree": 6.242277087749017,
                "motion_speed": 0.2255943386906247,
                "zodiac": 3,
                "house": 12,
                "motion": "D"
            },
            "Sun": {
                "degree": 52.86783269711158,
                "cusp_degree": 22.86783269711158,
                "motion_speed": 0.9567726808279764,
                "zodiac": 2,
                "house": 11,
                "motion": "D"
            },
            "Moon": {
                "degree": 339.80482398119517,
                "cusp_degree": 9.80482398119517,
                "motion_speed": 12.63067056442572,
                "zodiac": 12,
                "house": 9,
                "motion": "D"
            },
            "Venus": {
                "degree": 13.014376941296357,
                "cusp_degree": 13.014376941296357,
                "motion_speed": 1.1487078819420344,
                "zodiac": 1,
                "house": 10,
                "motion": "D"
            },
            "Mars": {
                "degree": 92.7244703967596,
                "cusp_degree": 2.7244703967595996,
                "motion_speed": 0.6162366009571446,
                "zodiac": 4,
                "house": 1,
                "motion": "D"
            },
            "Mercury": {
                "degree": 61.056346128828515,
                "cusp_degree": 1.0563461288285154,
                "motion_speed": -0.4295039318762511,
                "zodiac": 3,
                "house": 12,
                "motion": "R"
            },
            "Saturn": {
                "degree": 40.749682334964504,
                "cusp_degree": 10.749682334964504,
                "motion_speed": 0.1276100900595821,
                "zodiac": 2,
                "house": 11,
                "motion": "D"
            },
            "Rahu True": {
                "degree": 135.25268212591192,
                "cusp_degree": 15.252682125911917,
                "motion_speed": -0.026402486944229458,
                "zodiac": 5,
                "house": 2,
                "motion": "R"
            },
            "Rahu Mean": {
                "degree": 135.46078403543547,
                "cusp_degree": 15.460784035435466,
                "motion_speed": -0.05299206007328371,
                "zodiac": 5,
                "house": 2,
                "motion": "R"
            },
            "Ketu Mean": {
                "degree": 315.4607840354355,
                "motion_speed": -0.05299206007328371,
                "cusp_degree": 15.460784035435495,
                "zodiac": 11,
                "house": 8,
                "motion": "R"
            },
            "Ketu True": {
                "degree": 315.2526821259119,
                "motion_speed": -0.026402486944229458,
                "cusp_degree": 15.252682125911917,
                "zodiac": 11,
                "house": 8,
                "motion": "R"
            }
        }
    },
    "panchang": {
        "date": "1942-06-07",
        "latitude": 31.05926,
        "longitude": 16.65905,
        "time_zone": "Africa/Tripoli",
        "offset": 2,
        "julday": 2430517.5,
        "solar_longitude": 52.56551108949108,
        "lunar_longitude": 335.7991578616554,
        "lunar_latitude": -1.7718148941958192,
        "sunrise": [
            2430517.7455322416,
            [
                5,
                53,
                34
            ],
            [
                1942,
                6,
                7,
                5.892773799598217
            ]
        ],
        "sunset": [
            2430518.3267265386,
            [
                19,
                50,
                29
            ],
            [
                1942,
                6,
                7,
                19.84143692627549
            ]
        ],
        "moonrise": [
            2430517.5770896417,
            [
                1,
                51,
                1
            ],
            [
                1942,
                6,
                7,
                1.850151401013136
            ]
        ],
        "moonset": [
            2430518.095094722,
            [
                14,
                16,
                56
            ],
            [
                1942,
                6,
                7,
                14.282273333519697
            ]
        ],
        "tithi": [
            24,
            [
                15,
                42,
                13
            ]
        ],
        "nakshatra": [
            "Shatabhisha",
            24,
            [
                15,
                46,
                23
            ]
        ],
        "yoga": [
            "Ayushman",
            2
        ],
        "karana": [
            47,
            -4.113963642748615
        ],
        "vaara": "Ravivara",
        "lunar_phase": 283.2336467721643,
        "masa": [
            "Jyeshtha",
            3,
            false
        ],
        "ahargana": 1842052,
        "ritu": "Vasant Ritu (Spring)",
        "samvatsara": 16,
        "day_duration": [
            13.948663126677275,
            [
                13,
                56,
                55
            ]
        ]
    }
}